levseq_vis/__init__.py
levseq_vis/seqfit.py
levseq_vis/visualization.py
levseq_vis-1.2.6.data/data/LICENSE
levseq_vis-1.2.6.dist-info/LICENSE
levseq_vis-1.2.6.dist-info/METADATA
levseq_vis-1.2.6.dist-info/WHEEL
levseq_vis-1.2.6.dist-info/top_level.txt
levseq_vis-1.2.6.dist-info/RECORD
