Metadata-Version: 2.1
Name: levseq_vis
Version: 1.2.6
Home-page: https://github.com/fhalab/levseq/
Author: Yueming Long, Emreay Gursoy, Ariane Mora, Francesca-Zhoufan Li
Author-email: ylong@caltech.edu
License: GPL3
Project-URL: Bug Tracker, https://github.com/fhalab/levseq/
Project-URL: Documentation, https://github.com/fhalab/levseq/
Project-URL: Source Code, https://github.com/fhalab/levseq/
Keywords: Nanopore,ONT,evSeq,LevSeq
Classifier: Development Status :: 5 - Production/Stable
Classifier: Intended Audience :: Science/Research
Classifier: License :: OSI Approved :: GNU General Public License v3 (GPLv3)
Classifier: Natural Language :: English
Classifier: Operating System :: OS Independent
Classifier: Programming Language :: Python :: 3.6
Classifier: Programming Language :: Python :: 3.7
Classifier: Programming Language :: Python :: 3.8
Classifier: Topic :: Scientific/Engineering :: Bio-Informatics
Requires-Python: >=3.8
License-File: LICENSE
Requires-Dist: matplotlib
Requires-Dist: numpy
Requires-Dist: pandas
Requires-Dist: sciutil
Requires-Dist: seaborn
Requires-Dist: holoviews
Requires-Dist: ninetysix
Requires-Dist: scikit-learn
Requires-Dist: statsmodels
Requires-Dist: tqdm
